{
	"song": {
		"player1": "bfstream",
		"player2": "xaph",
		"notes": [
			{
				"lengthInSteps": 16,
				"sectionNotes": [],
				"mustHitSection": true
			},
			{
				"lengthInSteps": 16,
				"sectionNotes": [],
				"mustHitSection": true
			},
			{
				"lengthInSteps": 16,
				"sectionNotes": [],
				"mustHitSection": true
			},
			{
				"lengthInSteps": 16,
				"sectionNotes": [],
				"mustHitSection": true
			},
			{
				"lengthInSteps": 16,
				"sectionNotes": [
					[
						8076.92307692308,
						2,
						0
					],
					[
						8140.38461538462,
						1,
						0
					],
					[
						8769.23076923077,
						1,
						348
					],
					[
						8769.23076923077,
						0,
						0
					],
					[
						8192.30769230769,
						0,
						0
					],
					[
						8307.69230769231,
						1,
						116
					],
					[
						8538.46153846154,
						3,
						116
					],
					[
						8538.46153846154,
						2,
						0
					],
					[
						7615.38461538462,
						0,
						0
					],
					[
						7730.76923076923,
						3,
						0
					],
					[
						7846.15384615385,
						0,
						0
					]
				],
				"mustHitSection": false
			},
			{
				"lengthInSteps": 16,
				"sectionNotes": [
					[
						9230.76923076923,
						0,
						0
					],
					[
						9346.15384615385,
						3,
						0
					],
					[
						9923.07692307692,
						3,
						0
					],
					[
						10615.3846153846,
						3,
						0
					],
					[
						10730.7692307692,
						0,
						0
					],
					[
						9692.30769230769,
						0,
						0
					],
					[
						9807.69230769231,
						2,
						0
					],
					[
						9461.53846153846,
						2,
						116
					],
					[
						10038.4615384615,
						3,
						0
					],
					[
						10153.8461538462,
						1,
						116
					],
					[
						10384.6153846154,
						2,
						116
					],
					[
						10846.1538461538,
						1,
						116
					]
				],
				"mustHitSection": false
			},
			{
				"lengthInSteps": 16,
				"sectionNotes": [
					[
						11307.6923076923,
						3,
						0
					],
					[
						11423.0769230769,
						0,
						0
					],
					[
						11538.4615384615,
						1,
						0
					],
					[
						11884.6153846154,
						0,
						0
					],
					[
						12000,
						2,
						0
					],
					[
						12115.3846153846,
						1,
						0
					],
					[
						11653.8461538462,
						3,
						0
					],
					[
						12230.7692307692,
						3,
						116
					],
					[
						12461.5384615385,
						0,
						0
					],
					[
						12692.3076923077,
						2,
						116
					],
					[
						12692.3076923077,
						3,
						0
					]
				],
				"mustHitSection": false
			},
			{
				"lengthInSteps": 16,
				"sectionNotes": [
					[
						13615.3846153846,
						1,
						0
					],
					[
						13846.1538461538,
						2,
						116
					],
					[
						14076.9230769231,
						0,
						116
					],
					[
						14307.6923076923,
						3,
						116
					],
					[
						13846.1538461538,
						1,
						0
					],
					[
						14307.6923076923,
						2,
						0
					],
					[
						13038.4615384615,
						1,
						0
					],
					[
						12923.0769230769,
						0,
						116
					],
					[
						13153.8461538462,
						2,
						116
					],
					[
						13384.6153846154,
						3,
						0
					],
					[
						14538.4615384615,
						0,
						0
					]
				],
				"mustHitSection": false
			},
			{
				"lengthInSteps": 16,
				"sectionNotes": [
					[
						14769.2307692308,
						5,
						348
					],
					[
						15576.9230769231,
						6,
						580
					],
					[
						16269.2307692308,
						4,
						696
					],
					[
						15461.5384615385,
						2,
						0
					],
					[
						15525,
						1,
						0
					],
					[
						16153.8461538462,
						1,
						348
					],
					[
						16153.8461538462,
						0,
						0
					],
					[
						15576.9230769231,
						0,
						0
					],
					[
						15692.3076923077,
						1,
						116
					],
					[
						15923.0769230769,
						3,
						116
					],
					[
						15923.0769230769,
						2,
						0
					],
					[
						15000,
						0,
						0
					],
					[
						15115.3846153846,
						3,
						0
					],
					[
						15230.7692307692,
						0,
						0
					]
				],
				"mustHitSection": true
			},
			{
				"lengthInSteps": 16,
				"sectionNotes": [
					[
						17076.9230769231,
						6,
						232
					],
					[
						17538.4615384615,
						5,
						349
					],
					[
						18000,
						6,
						116
					],
					[
						16615.3846153846,
						0,
						0
					],
					[
						16730.7692307692,
						3,
						0
					],
					[
						17307.6923076923,
						3,
						0
					],
					[
						18000,
						3,
						0
					],
					[
						18115.3846153846,
						0,
						0
					],
					[
						17076.9230769231,
						0,
						0
					],
					[
						17192.3076923077,
						2,
						0
					],
					[
						16846.1538461538,
						2,
						116
					],
					[
						17423.0769230769,
						3,
						0
					],
					[
						17538.4615384615,
						1,
						116
					],
					[
						17769.2307692308,
						2,
						116
					],
					[
						18230.7692307692,
						1,
						116
					],
					[
						18230.7692307692,
						4,
						232
					]
				],
				"mustHitSection": true
			},
			{
				"lengthInSteps": 16,
				"sectionNotes": [
					[
						18692.3076923077,
						3,
						0
					],
					[
						18807.6923076923,
						0,
						0
					],
					[
						18923.0769230769,
						1,
						0
					],
					[
						19269.2307692308,
						0,
						0
					],
					[
						19384.6153846154,
						2,
						0
					],
					[
						19500,
						1,
						0
					],
					[
						19038.4615384615,
						3,
						0
					],
					[
						19615.3846153846,
						3,
						116
					],
					[
						19846.1538461538,
						0,
						0
					],
					[
						20076.9230769231,
						2,
						116
					],
					[
						20076.9230769231,
						3,
						0
					],
					[
						18576.9230769231,
						4,
						232
					],
					[
						18461.5384615385,
						5,
						232
					]
				],
				"mustHitSection": true
			},
			{
				"lengthInSteps": 16,
				"sectionNotes": [
					[
						21000,
						1,
						0
					],
					[
						21230.7692307692,
						2,
						116
					],
					[
						21461.5384615385,
						0,
						116
					],
					[
						21692.3076923077,
						3,
						116
					],
					[
						21230.7692307692,
						1,
						0
					],
					[
						21692.3076923077,
						2,
						0
					],
					[
						20423.0769230769,
						1,
						0
					],
					[
						20307.6923076923,
						0,
						116
					],
					[
						20538.4615384615,
						2,
						116
					],
					[
						20769.2307692308,
						3,
						0
					],
					[
						21923.0769230769,
						0,
						0
					],
					[
						20307.6923076923,
						6,
						348
					],
					[
						20769.2307692308,
						4,
						348
					],
					[
						21230.7692307692,
						5,
						0
					],
					[
						21461.5384615385,
						5,
						0
					],
					[
						21692.3076923077,
						6,
						116
					],
					[
						21923.0769230769,
						7,
						0
					]
				],
				"mustHitSection": true
			},
			{
				"lengthInSteps": 16,
				"sectionNotes": [
					[
						22153.8461538462,
						6,
						467
					],
					[
						23538.4615384615,
						3,
						0
					],
					[
						23307.6923076923,
						1,
						0
					],
					[
						23769.2307692308,
						2,
						0
					],
					[
						22153.8461538462,
						0,
						0
					],
					[
						22384.6153846154,
						0,
						116
					],
					[
						22615.3846153846,
						1,
						0
					],
					[
						22846.1538461538,
						1,
						116
					],
					[
						23076.9230769231,
						2,
						116
					]
				],
				"mustHitSection": false
			},
			{
				"lengthInSteps": 16,
				"sectionNotes": [
					[
						24000,
						1,
						0
					],
					[
						24115.3846153846,
						1,
						0
					],
					[
						25153.8461538462,
						1,
						0
					],
					[
						24692.3076923077,
						1,
						0
					],
					[
						25269.2307692308,
						1,
						0
					],
					[
						25615.3846153846,
						2,
						0
					],
					[
						24346.1538461539,
						2,
						116
					],
					[
						24923.0769230769,
						3,
						116
					],
					[
						25384.6153846154,
						0,
						0
					]
				],
				"mustHitSection": false
			},
			{
				"lengthInSteps": 16,
				"sectionNotes": [
					[
						26769.2307692308,
						0,
						349
					],
					[
						27230.7692307692,
						1,
						0
					],
					[
						27346.1538461539,
						2,
						0
					],
					[
						27461.5384615385,
						3,
						0
					],
					[
						26538.4615384615,
						2,
						0
					],
					[
						26653.8461538462,
						1,
						0
					],
					[
						25846.1538461539,
						3,
						0
					],
					[
						26076.9230769231,
						2,
						116
					],
					[
						26307.6923076923,
						0,
						116
					],
					[
						27576.9230769231,
						0,
						0
					]
				],
				"mustHitSection": false
			},
			{
				"lengthInSteps": 16,
				"sectionNotes": [
					[
						28153.8461538462,
						0,
						0
					],
					[
						29076.9230769231,
						2,
						0
					],
					[
						28384.6153846154,
						2,
						0
					],
					[
						28846.1538461539,
						1,
						0
					],
					[
						28961.5384615385,
						1,
						0
					],
					[
						27692.3076923077,
						2,
						118
					],
					[
						27923.0769230769,
						3,
						0
					],
					[
						28615.3846153846,
						3,
						116
					],
					[
						29307.6923076923,
						3,
						0
					]
				],
				"mustHitSection": false
			},
			{
				"lengthInSteps": 16,
				"sectionNotes": [
					[
						30923.0769230769,
						3,
						0
					],
					[
						30692.3076923077,
						1,
						0
					],
					[
						31153.8461538462,
						2,
						0
					],
					[
						29538.4615384615,
						0,
						0
					],
					[
						29769.2307692308,
						0,
						116
					],
					[
						30000,
						1,
						0
					],
					[
						30230.7692307692,
						1,
						116
					],
					[
						30461.5384615385,
						2,
						116
					],
					[
						29538.4615384615,
						6,
						814
					],
					[
						30923.0769230769,
						4,
						697
					]
				],
				"mustHitSection": true
			},
			{
				"lengthInSteps": 16,
				"sectionNotes": [
					[
						31384.6153846154,
						1,
						0
					],
					[
						31500,
						1,
						0
					],
					[
						32538.4615384616,
						1,
						0
					],
					[
						32076.9230769231,
						1,
						0
					],
					[
						32653.8461538462,
						1,
						0
					],
					[
						33000,
						2,
						0
					],
					[
						31730.7692307692,
						2,
						116
					],
					[
						32307.6923076923,
						3,
						116
					],
					[
						32769.2307692308,
						0,
						0
					],
					[
						32307.6923076923,
						5,
						814
					]
				],
				"mustHitSection": true
			},
			{
				"lengthInSteps": 16,
				"sectionNotes": [
					[
						34153.8461538462,
						0,
						349
					],
					[
						34615.3846153846,
						1,
						0
					],
					[
						34730.7692307693,
						2,
						0
					],
					[
						34846.1538461539,
						3,
						0
					],
					[
						33923.0769230769,
						2,
						0
					],
					[
						34038.4615384616,
						1,
						0
					],
					[
						33230.7692307692,
						3,
						0
					],
					[
						33461.5384615385,
						2,
						116
					],
					[
						33692.3076923077,
						0,
						116
					],
					[
						34961.5384615385,
						0,
						0
					],
					[
						33230.7692307692,
						7,
						930
					],
					[
						34615.3846153846,
						6,
						928
					]
				],
				"mustHitSection": true
			},
			{
				"lengthInSteps": 16,
				"sectionNotes": [
					[
						35538.4615384616,
						0,
						0
					],
					[
						36461.5384615385,
						2,
						0
					],
					[
						35769.2307692308,
						2,
						0
					],
					[
						36230.7692307693,
						1,
						0
					],
					[
						36346.1538461539,
						1,
						0
					],
					[
						35076.9230769231,
						2,
						118
					],
					[
						35307.6923076923,
						3,
						0
					],
					[
						36000,
						3,
						116
					],
					[
						36692.3076923077,
						3,
						0
					],
					[
						36000,
						5,
						812
					]
				],
				"mustHitSection": true
			},
			{
				"lengthInSteps": 16,
				"sectionNotes": [],
				"mustHitSection": true
			},
			{
				"lengthInSteps": 16,
				"sectionNotes": [],
				"mustHitSection": false
			},
			{
				"lengthInSteps": 16,
				"sectionNotes": [],
				"mustHitSection": true
			},
			{
				"lengthInSteps": 16,
				"sectionNotes": [],
				"mustHitSection": false
			},
			{
				"lengthInSteps": 16,
				"sectionNotes": [],
				"mustHitSection": true
			},
			{
				"lengthInSteps": 16,
				"sectionNotes": [],
				"mustHitSection": false
			},
			{
				"lengthInSteps": 16,
				"sectionNotes": [],
				"mustHitSection": true
			},
			{
				"lengthInSteps": 16,
				"sectionNotes": [],
				"sectionBeats": 4,
				"mustHitSection": false
			},
			{
				"lengthInSteps": 16,
				"sectionNotes": [],
				"sectionBeats": 2,
				"mustHitSection": true
			},
			{
				"lengthInSteps": 16,
				"sectionNotes": [
					[
						52846.1538461538,
						0,
						0
					],
					[
						52961.5384615384,
						3,
						0
					],
					[
						53076.9230769231,
						0,
						0
					],
					[
						53423.0769230769,
						0,
						0
					],
					[
						53365.3846153846,
						1,
						0
					],
					[
						53307.6923076923,
						2,
						0
					],
					[
						53538.4615384615,
						3,
						0
					],
					[
						53538.4615384615,
						2,
						0
					],
					[
						53769.2307692308,
						1,
						0
					],
					[
						53769.2307692308,
						0,
						0
					],
					[
						54000,
						1,
						0
					],
					[
						54000,
						2,
						348
					]
				],
				"mustHitSection": false
			},
			{
				"lengthInSteps": 16,
				"sectionNotes": [
					[
						54461.5384615384,
						1,
						0
					],
					[
						54576.9230769231,
						1,
						0
					],
					[
						54692.3076923077,
						3,
						116
					],
					[
						54923.0769230769,
						2,
						0
					],
					[
						55038.4615384615,
						0,
						0
					],
					[
						55153.8461538461,
						1,
						0
					],
					[
						55269.2307692308,
						3,
						0
					],
					[
						55384.6153846154,
						2,
						116
					],
					[
						55615.3846153846,
						0,
						116
					],
					[
						55846.1538461538,
						1,
						0
					],
					[
						55961.5384615384,
						3,
						0
					],
					[
						56076.9230769231,
						2,
						116
					]
				],
				"mustHitSection": false
			},
			{
				"lengthInSteps": 16,
				"sectionNotes": [
					[
						56538.4615384615,
						0,
						0
					],
					[
						56653.8461538461,
						0,
						0
					],
					[
						56769.2307692308,
						2,
						0
					],
					[
						56884.6153846154,
						1,
						0
					],
					[
						57115.3846153846,
						3,
						0
					],
					[
						57230.7692307692,
						2,
						0
					],
					[
						57346.1538461538,
						0,
						0
					],
					[
						57461.5384615384,
						1,
						116
					],
					[
						57692.3076923077,
						3,
						0
					],
					[
						57923.0769230769,
						2,
						116
					]
				],
				"mustHitSection": false
			},
			{
				"lengthInSteps": 16,
				"sectionNotes": [
					[
						58153.8461538461,
						0,
						116
					],
					[
						58384.6153846154,
						2,
						116
					],
					[
						58615.3846153846,
						3,
						0
					],
					[
						58846.1538461538,
						1,
						0
					],
					[
						59076.9230769231,
						0,
						0
					],
					[
						59076.9230769231,
						2,
						0
					],
					[
						59307.6923076923,
						2,
						0
					],
					[
						59307.6923076923,
						3,
						0
					],
					[
						59538.4615384615,
						1,
						116
					],
					[
						59769.2307692308,
						0,
						116
					]
				],
				"mustHitSection": false
			},
			{
				"lengthInSteps": 16,
				"sectionNotes": [
					[
						60000,
						6,
						464
					],
					[
						60230.7692307692,
						0,
						0
					],
					[
						60346.1538461538,
						3,
						0
					],
					[
						60461.5384615384,
						0,
						0
					],
					[
						60807.6923076923,
						0,
						0
					],
					[
						60750,
						1,
						0
					],
					[
						60692.3076923077,
						2,
						0
					],
					[
						60923.0769230769,
						3,
						0
					],
					[
						60923.0769230769,
						2,
						0
					],
					[
						61153.8461538461,
						1,
						0
					],
					[
						61153.8461538461,
						0,
						0
					],
					[
						61384.6153846154,
						1,
						0
					],
					[
						61384.6153846154,
						2,
						348
					]
				],
				"mustHitSection": true
			},
			{
				"lengthInSteps": 16,
				"sectionNotes": [
					[
						61846.1538461538,
						1,
						0
					],
					[
						61961.5384615384,
						1,
						0
					],
					[
						62076.9230769231,
						3,
						116
					],
					[
						62307.6923076923,
						2,
						0
					],
					[
						62423.0769230769,
						0,
						0
					],
					[
						62538.4615384615,
						1,
						0
					],
					[
						62653.8461538461,
						3,
						0
					],
					[
						62769.2307692308,
						2,
						116
					],
					[
						63000,
						0,
						116
					],
					[
						63230.7692307692,
						1,
						0
					],
					[
						63346.1538461538,
						3,
						0
					],
					[
						63461.5384615384,
						2,
						116
					]
				],
				"mustHitSection": true
			},
			{
				"lengthInSteps": 16,
				"sectionNotes": [
					[
						63923.0769230769,
						0,
						0
					],
					[
						64038.4615384615,
						0,
						0
					],
					[
						64153.8461538461,
						2,
						0
					],
					[
						64269.2307692308,
						1,
						0
					],
					[
						64500,
						3,
						0
					],
					[
						64615.3846153846,
						2,
						0
					],
					[
						64730.7692307692,
						0,
						0
					],
					[
						64846.1538461538,
						1,
						116
					],
					[
						65076.9230769231,
						3,
						0
					],
					[
						65307.6923076923,
						2,
						116
					]
				],
				"mustHitSection": true
			},
			{
				"lengthInSteps": 16,
				"sectionNotes": [
					[
						65538.4615384615,
						0,
						116
					],
					[
						65769.2307692308,
						2,
						116
					],
					[
						66000,
						3,
						0
					],
					[
						66230.7692307692,
						1,
						0
					],
					[
						66461.5384615384,
						0,
						0
					],
					[
						66461.5384615384,
						2,
						0
					],
					[
						66692.3076923077,
						2,
						0
					],
					[
						66692.3076923077,
						3,
						0
					],
					[
						66923.0769230769,
						1,
						116
					],
					[
						67153.8461538461,
						0,
						116
					]
				],
				"mustHitSection": true
			},
			{
				"lengthInSteps": 16,
				"sectionNotes": [
					[
						69000,
						2,
						0
					],
					[
						67384.6153846154,
						6,
						349
					],
					[
						67615.3846153846,
						0,
						0
					],
					[
						67730.7692307692,
						0,
						0
					],
					[
						67846.1538461538,
						3,
						116
					],
					[
						68076.923076923,
						1,
						116
					],
					[
						68307.6923076923,
						2,
						0
					],
					[
						68538.4615384615,
						0,
						116
					],
					[
						68769.2307692308,
						1,
						0
					],
					[
						68884.6153846154,
						3,
						0
					]
				],
				"mustHitSection": false
			},
			{
				"lengthInSteps": 16,
				"sectionNotes": [
					[
						69230.7692307692,
						0,
						116
					],
					[
						69461.5384615384,
						1,
						0
					],
					[
						69692.3076923077,
						2,
						116
					],
					[
						70153.8461538461,
						0,
						0
					],
					[
						70384.6153846154,
						1,
						116
					],
					[
						70846.1538461538,
						0,
						0
					],
					[
						69923.0769230769,
						1,
						0
					],
					[
						70615.3846153846,
						3,
						116
					]
				],
				"mustHitSection": false
			},
			{
				"lengthInSteps": 16,
				"sectionNotes": [
					[
						72692.3076923077,
						2,
						0
					],
					[
						71307.6923076923,
						0,
						0
					],
					[
						71423.0769230769,
						0,
						0
					],
					[
						71538.4615384615,
						3,
						116
					],
					[
						71769.2307692307,
						1,
						116
					],
					[
						72000,
						2,
						0
					],
					[
						72230.7692307692,
						0,
						116
					],
					[
						72461.5384615384,
						1,
						0
					],
					[
						72576.923076923,
						3,
						0
					],
					[
						71538.4615384615,
						6,
						348
					],
					[
						72461.5384615384,
						4,
						348
					]
				],
				"mustHitSection": true
			},
			{
				"lengthInSteps": 16,
				"sectionNotes": [
					[
						72923.0769230769,
						0,
						116
					],
					[
						73153.8461538461,
						1,
						0
					],
					[
						73384.6153846154,
						2,
						116
					],
					[
						73846.1538461538,
						0,
						0
					],
					[
						74076.923076923,
						1,
						116
					],
					[
						74538.4615384615,
						0,
						0
					],
					[
						73615.3846153846,
						1,
						0
					],
					[
						74307.6923076923,
						3,
						116
					],
					[
						73384.6153846154,
						5,
						348
					],
					[
						73846.1538461538,
						7,
						348
					],
					[
						74307.6923076923,
						6,
						348
					]
				],
				"mustHitSection": true
			},
			{
				"lengthInSteps": 16,
				"sectionNotes": [
					[
						75000,
						1,
						0
					],
					[
						75115.3846153846,
						1,
						0
					],
					[
						75230.7692307692,
						6,
						348
					],
					[
						75230.7692307692,
						2,
						0
					],
					[
						75461.5384615384,
						0,
						0
					],
					[
						75692.3076923077,
						1,
						117
					],
					[
						75923.0769230769,
						3,
						0
					],
					[
						76153.8461538461,
						2,
						348
					],
					[
						76153.8461538461,
						4,
						348
					]
				],
				"mustHitSection": false
			},
			{
				"lengthInSteps": 16,
				"sectionNotes": [
					[
						76615.3846153846,
						0,
						348
					],
					[
						77076.923076923,
						1,
						118
					],
					[
						77307.6923076923,
						2,
						0
					],
					[
						77538.4615384615,
						1,
						116
					],
					[
						77769.2307692307,
						3,
						0
					],
					[
						78000,
						2,
						116
					],
					[
						78230.7692307692,
						0,
						0
					]
				],
				"mustHitSection": false
			},
			{
				"lengthInSteps": 16,
				"sectionNotes": [
					[
						78692.3076923077,
						1,
						0
					],
					[
						78807.6923076923,
						1,
						0
					],
					[
						78923.0769230769,
						2,
						0
					],
					[
						79153.8461538461,
						0,
						0
					],
					[
						79384.6153846153,
						1,
						117
					],
					[
						79615.3846153846,
						3,
						0
					],
					[
						79846.1538461538,
						2,
						348
					],
					[
						78461.5384615384,
						6,
						348
					]
				],
				"mustHitSection": true
			},
			{
				"lengthInSteps": 16,
				"sectionNotes": [
					[
						80307.6923076923,
						0,
						348
					],
					[
						80769.2307692307,
						1,
						118
					],
					[
						81000,
						2,
						0
					],
					[
						81230.7692307692,
						1,
						116
					],
					[
						81461.5384615384,
						3,
						0
					],
					[
						81692.3076923077,
						2,
						116
					],
					[
						81923.0769230769,
						0,
						0
					]
				],
				"mustHitSection": true
			},
			{
				"lengthInSteps": 16,
				"sectionNotes": [
					[
						82153.8461538461,
						3,
						1740
					]
				],
				"mustHitSection": true
			},
			{
				"lengthInSteps": 16,
				"sectionNotes": [],
				"mustHitSection": false
			},
			{
				"lengthInSteps": 16,
				"sectionNotes": [],
				"mustHitSection": true
			},
			{
				"lengthInSteps": 16,
				"sectionNotes": [],
				"mustHitSection": false
			},
			{
				"lengthInSteps": 16,
				"sectionNotes": [],
				"mustHitSection": true
			},
			{
				"lengthInSteps": 16,
				"sectionNotes": [],
				"mustHitSection": false
			},
			{
				"lengthInSteps": 16,
				"sectionNotes": [],
				"mustHitSection": false
			},
			{
				"lengthInSteps": 16,
				"sectionNotes": [],
				"mustHitSection": true
			},
			{
				"lengthInSteps": 16,
				"sectionNotes": [],
				"mustHitSection": true
			},
			{
				"lengthInSteps": 16,
				"sectionNotes": [],
				"mustHitSection": true
			},
			{
				"lengthInSteps": 16,
				"sectionNotes": [],
				"mustHitSection": true
			},
			{
				"lengthInSteps": 16,
				"sectionNotes": [],
				"mustHitSection": false
			},
			{
				"lengthInSteps": 16,
				"sectionNotes": [],
				"mustHitSection": false
			},
			{
				"lengthInSteps": 16,
				"sectionNotes": [],
				"mustHitSection": true
			},
			{
				"lengthInSteps": 16,
				"sectionNotes": [],
				"mustHitSection": true
			},
			{
				"lengthInSteps": 16,
				"sectionNotes": [],
				"mustHitSection": false
			},
			{
				"lengthInSteps": 16,
				"sectionNotes": [],
				"mustHitSection": false
			},
			{
				"lengthInSteps": 16,
				"sectionNotes": [],
				"mustHitSection": true
			},
			{
				"lengthInSteps": 16,
				"sectionNotes": [],
				"mustHitSection": true
			},
			{
				"lengthInSteps": 16,
				"sectionNotes": [],
				"mustHitSection": true
			}
		],
		"gfVersion": "air",
		"events": [],
		"player3": null,
		"gameOverChar": "directogo",
		"song": "Directo",
		"needsVoices": true,
		"stage": "stream",
		"speed": 2.7,
		"bpm": 130
	}
}